rvcpy/EN1990.py
rvcpy/GaussWeightsAndPoints.py
rvcpy/GlobalAux.py
rvcpy/LatinHypercube.py
rvcpy/MaxEnt_testing.py
rvcpy/PrintAuxiliary.py
rvcpy/__init__.py
rvcpy/k_reduxTheta.py
rvcpy/probabCalc.py
rvcpy/probabCalc_2018.py
rvcpy/statFunc.py
rvcpy/tester.py
rvcpy/visualization.py
rvcpy-0.0.2.dist-info/LICENSE
rvcpy-0.0.2.dist-info/METADATA
rvcpy-0.0.2.dist-info/WHEEL
rvcpy-0.0.2.dist-info/top_level.txt
rvcpy-0.0.2.dist-info/RECORD
