Metadata-Version: 2.1
Name: rvcpy
Version: 0.0.2
Summary: rvc basic functionality
Home-page: https://github.com/rvcoile/rvcpy
Author: Ruben Van Coile
Author-email: ruben.vancoile@gmail.com
License: UNKNOWN
Platform: UNKNOWN
Classifier: Programming Language :: Python :: 3
Classifier: License :: OSI Approved :: MIT License
Classifier: Operating System :: OS Independent
